HammrahAval/HammrahAval.py
HammrahAval/__init__.py
HammrahAval/config.py
HammrahAval_python-1.0.1.dist-info/LICENSE
HammrahAval_python-1.0.1.dist-info/METADATA
HammrahAval_python-1.0.1.dist-info/WHEEL
HammrahAval_python-1.0.1.dist-info/top_level.txt
HammrahAval_python-1.0.1.dist-info/RECORD
