Metadata-Version: 2.2
Name: HammrahAval-python
Version: 1.0.1
Summary: A library for HammrahAval Application
Home-page: https://github.com/ItsOkp-TM/HammrahAval
Author: Sepehr Dehghan
Author-email: sepehrbiggamer@gmail.com
Classifier: Programming Language :: Python :: 3
Classifier: License :: OSI Approved :: MIT License
Classifier: Operating System :: OS Independent
Requires-Python: >=3.6
License-File: LICENSE
Dynamic: author
Dynamic: author-email
Dynamic: classifier
Dynamic: description-content-type
Dynamic: home-page
Dynamic: requires-python
Dynamic: summary
